LICENSE
NOTICE
README.rst
setup.cfg
setup.py
git_remote_codecommit/__init__.py
git_remote_codecommit.egg-info/PKG-INFO
git_remote_codecommit.egg-info/SOURCES.txt
git_remote_codecommit.egg-info/dependency_links.txt
git_remote_codecommit.egg-info/entry_points.txt
git_remote_codecommit.egg-info/requires.txt
git_remote_codecommit.egg-info/top_level.txt