Metadata-Version: 2.1
Name: git-remote-codecommit
Version: 1.17
Summary: Git remote prefix to simplify pushing to and pulling from CodeCommit.
Home-page: https://github.com/awslabs/git-remote-codecommit
Author: Amazon Web Services
License: Apache License 2.0
Classifier: Development Status :: 5 - Production/Stable
Classifier: Intended Audience :: Developers
Classifier: Topic :: Utilities
Classifier: License :: OSI Approved :: Apache Software License
License-File: LICENSE
License-File: NOTICE
